pypdfium2/__init__.py
pypdfium2/__main__.py
pypdfium2/_lazy.py
pypdfium2/_library_scope.py
pypdfium2/raw.py
pypdfium2/version.json
pypdfium2/version.py
pypdfium2/_cli/__init__.py
pypdfium2/_cli/_parsers.py
pypdfium2/_cli/arrange.py
pypdfium2/_cli/attachments.py
pypdfium2/_cli/extract_images.py
pypdfium2/_cli/extract_text.py
pypdfium2/_cli/imgtopdf.py
pypdfium2/_cli/pageobjects.py
pypdfium2/_cli/pdfinfo.py
pypdfium2/_cli/render.py
pypdfium2/_cli/tile.py
pypdfium2/_cli/toc.py
pypdfium2/_helpers/__init__.py
pypdfium2/_helpers/attachment.py
pypdfium2/_helpers/bitmap.py
pypdfium2/_helpers/document.py
pypdfium2/_helpers/matrix.py
pypdfium2/_helpers/misc.py
pypdfium2/_helpers/page.py
pypdfium2/_helpers/pageobjects.py
pypdfium2/_helpers/textpage.py
pypdfium2/_helpers/unsupported.py
pypdfium2/internal/__init__.py
pypdfium2/internal/bases.py
pypdfium2/internal/consts.py
pypdfium2/internal/utils.py
pypdfium2-5.3.0.dist-info/licenses/LICENSES/Apache-2.0.txt
pypdfium2-5.3.0.dist-info/licenses/LICENSES/BSD-3-Clause.txt
pypdfium2-5.3.0.dist-info/licenses/LICENSES/CC-BY-4.0.txt
pypdfium2-5.3.0.dist-info/licenses/data/darwin_arm64/BUILD_LICENSES/abseil.txt
pypdfium2-5.3.0.dist-info/licenses/data/darwin_arm64/BUILD_LICENSES/agg23.txt
pypdfium2-5.3.0.dist-info/licenses/data/darwin_arm64/BUILD_LICENSES/fast_float.txt
pypdfium2-5.3.0.dist-info/licenses/data/darwin_arm64/BUILD_LICENSES/freetype.txt
pypdfium2-5.3.0.dist-info/licenses/data/darwin_arm64/BUILD_LICENSES/icu.txt
pypdfium2-5.3.0.dist-info/licenses/data/darwin_arm64/BUILD_LICENSES/lcms.txt
pypdfium2-5.3.0.dist-info/licenses/data/darwin_arm64/BUILD_LICENSES/libjpeg_turbo.ijg
pypdfium2-5.3.0.dist-info/licenses/data/darwin_arm64/BUILD_LICENSES/libjpeg_turbo.md
pypdfium2-5.3.0.dist-info/licenses/data/darwin_arm64/BUILD_LICENSES/libopenjpeg.txt
pypdfium2-5.3.0.dist-info/licenses/data/darwin_arm64/BUILD_LICENSES/libpng.txt
pypdfium2-5.3.0.dist-info/licenses/data/darwin_arm64/BUILD_LICENSES/libtiff.txt
pypdfium2-5.3.0.dist-info/licenses/data/darwin_arm64/BUILD_LICENSES/llvm-libc.txt
pypdfium2-5.3.0.dist-info/licenses/data/darwin_arm64/BUILD_LICENSES/pdfium-binaries.txt
pypdfium2-5.3.0.dist-info/licenses/data/darwin_arm64/BUILD_LICENSES/pdfium.txt
pypdfium2-5.3.0.dist-info/licenses/data/darwin_arm64/BUILD_LICENSES/zlib.txt
pypdfium2_raw/__init__.py
pypdfium2_raw/bindings.py
pypdfium2_raw/libpdfium.dylib
pypdfium2_raw/version.json
pypdfium2-5.3.0.dist-info/METADATA
pypdfium2-5.3.0.dist-info/WHEEL
pypdfium2-5.3.0.dist-info/entry_points.txt
pypdfium2-5.3.0.dist-info/top_level.txt
pypdfium2-5.3.0.dist-info/RECORD
