Metadata-Version: 2.4
Name: pypdfium2
Version: 5.3.0
Summary: Python bindings to PDFium
Home-page: https://github.com/pypdfium2-team/pypdfium2
Author: pypdfium2-team
Author-email: geisserml@gmail.com
License: BSD-3-Clause, Apache-2.0, dependency licenses
Project-URL: Source, https://github.com/pypdfium2-team/pypdfium2
Project-URL: Tracker, https://github.com/pypdfium2-team/pypdfium2/issues
Project-URL: Documentation, https://pypdfium2.readthedocs.io
Project-URL: Changelog, https://pypdfium2.readthedocs.io/en/stable/changelog.html
Keywords: pdf,pdfium
Classifier: Development Status :: 5 - Production/Stable
Classifier: Intended Audience :: Developers
Classifier: Intended Audience :: Information Technology
Classifier: Programming Language :: Python :: 3
Classifier: Programming Language :: Python :: 3 :: Only
Classifier: Programming Language :: Python :: Implementation :: CPython
Classifier: Topic :: Multimedia :: Graphics
Classifier: Topic :: Software Development :: Libraries
Requires-Python: >= 3.6
License-File: LICENSES/Apache-2.0.txt
License-File: LICENSES/BSD-3-Clause.txt
License-File: LICENSES/CC-BY-4.0.txt
License-File: data/windows_x86/BUILD_LICENSES/abseil.txt
License-File: data/windows_x86/BUILD_LICENSES/agg23.txt
License-File: data/windows_x86/BUILD_LICENSES/fast_float.txt
License-File: data/windows_x86/BUILD_LICENSES/freetype.txt
License-File: data/windows_x86/BUILD_LICENSES/icu.txt
License-File: data/windows_x86/BUILD_LICENSES/lcms.txt
License-File: data/windows_x86/BUILD_LICENSES/libjpeg_turbo.ijg
License-File: data/windows_x86/BUILD_LICENSES/libjpeg_turbo.md
License-File: data/windows_x86/BUILD_LICENSES/libopenjpeg.txt
License-File: data/windows_x86/BUILD_LICENSES/libpng.txt
License-File: data/windows_x86/BUILD_LICENSES/libtiff.txt
License-File: data/windows_x86/BUILD_LICENSES/llvm-libc.txt
License-File: data/windows_x86/BUILD_LICENSES/pdfium-binaries.txt
License-File: data/windows_x86/BUILD_LICENSES/pdfium.txt
License-File: data/windows_x86/BUILD_LICENSES/zlib.txt
Dynamic: license
Dynamic: license-file
Dynamic: requires-python
Dynamic: summary
